Compiled from "Paren.scala"
public final class Paren$ {
  public static final Paren$ MODULE$;

  public static {};
    Code:
       0: new           #2                  // class Paren$
       3: invokespecial #12                 // Method "<init>":()V
       6: return        

  public boolean balance(scala.collection.immutable.List<java.lang.Object>);
    Code:
       0: aload_0       
       1: iconst_0      
       2: aload_1       
       3: invokevirtual #18                 // Method count:(ILscala/collection/immutable/List;)Z
       6: ireturn       

  public boolean count(int, scala.collection.immutable.List<java.lang.Object>);
    Code:
       0: new           #23                 // class scala/Tuple2
       3: dup           
       4: iload_1       
       5: invokestatic  #29                 // Method scala/runtime/BoxesRunTime.boxToInteger:(I)Ljava/lang/Integer;
       8: aload_2       
       9: invokespecial #32                 // Method scala/Tuple2."<init>":(Ljava/lang/Object;Ljava/lang/Object;)V
      12: astore        4
      14: aload         4
      16: ifnull        57
      19: aload         4
      21: invokevirtual #36                 // Method scala/Tuple2._2:()Ljava/lang/Object;
      24: checkcast     #38                 // class scala/collection/immutable/List
      27: astore        5
      29: aload         5
      31: instanceof    #40                 // class scala/collection/immutable/$colon$colon
      34: ifeq          57
      37: aload         5
      39: checkcast     #40                 // class scala/collection/immutable/$colon$colon
      42: astore        6
      44: aload         6
      46: invokevirtual #44                 // Method scala/collection/immutable/$colon$colon.tl$1:()Lscala/collection/immutable/List;
      49: astore        7
      51: aload         7
      53: astore_2      
      54: goto          0
      57: iconst_0      
      58: istore        8
      60: iload         8
      62: ireturn       

  public void main(java.lang.String[]);
    Code:
       0: getstatic     #54                 // Field scala/Console$.MODULE$:Lscala/Console$;
       3: aload_0       
       4: new           #56                 // class scala/collection/immutable/StringOps
       7: dup           
       8: getstatic     #61                 // Field scala/Predef$.MODULE$:Lscala/Predef$;
      11: aload_1       
      12: iconst_0      
      13: aaload        
      14: invokevirtual #65                 // Method scala/Predef$.augmentString:(Ljava/lang/String;)Ljava/lang/String;
      17: invokespecial #68                 // Method scala/collection/immutable/StringOps."<init>":(Ljava/lang/String;)V
      20: invokeinterface #73,  1           // InterfaceMethod scala/collection/TraversableOnce.toList:()Lscala/collection/immutable/List;
      25: invokevirtual #75                 // Method balance:(Lscala/collection/immutable/List;)Z
      28: invokestatic  #79                 // Method scala/runtime/BoxesRunTime.boxToBoolean:(Z)Ljava/lang/Boolean;
      31: invokevirtual #83                 // Method scala/Console$.println:(Ljava/lang/Object;)V
      34: return        
}
